{
  "test_name": "normal",
  "timestamp": "2026-04-23T13:04:09.778286",
  "total": 2,
  "passed": 2,
  "failed": 0,
  "avg_time": 167.8,
  "results": [
    {
      "question": "如何提高手术刀片耐用性",
      "success": true,
      "elapsed_seconds": 148.86,
      "report_length": 1443,
      "errors": [],
      "failure_stage": null,
      "report_preview": "# TRIZ 解决方案报告\n\n## 问题\n如何提高手术刀片耐用性\n\n## 核心矛盾\n手术刀片材料硬度与切割锋利度之间的矛盾存在物理矛盾\n\n## 推荐方案（按理想度排序）\n\n### 方案 1 [理想度: 0.82 | 问题匹配: 5/5 | 逻辑一致性: 5/5]\n**原理**: [15, 34]\n**标题**: 动态硬度梯度刀片设计\n**描述**: 设计一种具有动态硬度梯度的手术刀片，刀片刃口区域采用高硬度材料（如陶瓷涂层或金刚石涂层）以保持锋利度，而刀片主体采用韧性较好的材料以承受操作应力。借鉴发明原理15（动态性）和发明原理34（抛弃与再生），在刀片表面设计微纳米级硬度梯度结构，当刃口磨损时，通过医生的操作压力或组织接触，自动暴露出下一层更硬的材料层。这种设计类似于铅笔芯结构，外层磨损后露出新的锋利刃口。使用现有手术器械材料，通过多层复合涂层技术实现，无需引入新组件。具体实施：在现有不锈钢刀片基底上，通过物理气相沉积技术依次沉积不同硬度的纳米涂层，最外层为超硬耐磨层，中间层为过渡层，底层为结合层。当外层磨损后，中间层自动成为新的切割刃口，从而延长刀片使用寿命。\n**可行性**: 4",
      "expected": "success",
      "description": "医疗/机械"
    },
    {
      "question": "汽车发动机噪音大",
      "success": true,
      "elapsed_seconds": 186.73,
      "report_length": 1309,
      "errors": [],
      "failure_stage": null,
      "report_preview": "# TRIZ 解决方案报告\n\n## 问题\n汽车发动机噪音大\n\n## 核心矛盾\n发动机功率输出与噪音控制的矛盾存在物理矛盾\n\n## 推荐方案（按理想度排序）\n\n### 方案 1 [理想度: 0.82 | 问题匹配: 5/5 | 逻辑一致性: 5/5]\n**原理**: [1, 22, 33]\n**标题**: 基于并联杆系多维力传感器的发动机振动主动控制系统\n**描述**: 借鉴专利'基于并联杆系多维力传感器的多维力获取方法'中的并联杆系结构原理（发明原理1：分割），在发动机关键振动点安装多维力传感器阵列，实时监测发动机各方向的振动力和频率。利用现有电磁场资源（电磁场）作为控制场，在发动机支架和车身连接处安装电磁阻尼器，根据传感器反馈实时调整阻尼力，实现振动的主动抵消。系统采用分层控制架构，上层控制器根据发动机运行状态预测振动模式，下层控制器实时调整电磁阻尼参数，将振动能量转化为电能存储或耗散。利用现有隔音材料作为被动隔音层，形成主动-被动结合的减振降噪系统。该系统可降低发动机振动传递到车身的幅度达70%，同时不影响发动机功率输出。\n**可行性**: 4/5 | 风险: medium\n\n##",
      "expected": "success",
      "description": "机械"
    }
  ]
}